SampleDistribution_1/mod1.py
SampleDistribution_1/pkg1/mod3.py
SampleDistribution_1/pkg2/main.py
SampleDistribution_2/pkg1/mod2.py
NamespaceDistribution-0.0.2.dist-info/LICENSE
NamespaceDistribution-0.0.2.dist-info/METADATA
NamespaceDistribution-0.0.2.dist-info/WHEEL
NamespaceDistribution-0.0.2.dist-info/entry_points.txt
NamespaceDistribution-0.0.2.dist-info/top_level.txt
NamespaceDistribution-0.0.2.dist-info/RECORD
