Metadata-Version: 2.1
Name: NamespaceDistribution
Version: 0.0.2
Summary: A small example package
Home-page: https://github.com/jeffgoldszer/NamespaceDistribution
Author: Jeff Goldszer
Author-email: jeff.goldszer@gmail.com
License: MIT
Project-URL: Bug Tracker, https://github.com/jeffgoldszer/NamespaceDistribution/issues
Platform: any
Classifier: Programming Language :: Python :: 3
Classifier: License :: OSI Approved :: MIT License
Classifier: Operating System :: OS Independent
Classifier: Development Status :: 4 - Beta
Classifier: Intended Audience :: Developers
Requires-Python: >=3.3
License-File: LICENSE
